MANIFEST.in
README.md
setup.py
GameGridP.egg-info/PKG-INFO
GameGridP.egg-info/SOURCES.txt
GameGridP.egg-info/dependency_links.txt
GameGridP.egg-info/requires.txt
GameGridP.egg-info/top_level.txt
gamegridp/__init__.py
gamegridp/actor.py
gamegridp/gamegrid.py
gamegridp/gamegrid_actionbar.py
gamegridp/gamegrid_console.py
gamegridp/gamegrid_toolbar.py
gamegridp/keys.py
gamegridp/utils.py
gamegridp/data/down.png
gamegridp/data/left.png
gamegridp/data/pause.png
gamegridp/data/play.png
gamegridp/data/question.png
gamegridp/data/reset.png
gamegridp/data/right.png
gamegridp/data/run.png
gamegridp/data/up.png