Metadata-Version: 2.1
Name: GameGridP
Version: 0.4.0.15
Summary: An educational 2D Engine for Python
Home-page: https://github.com/asbl/gamegridp
Author: Andreas Siebel
Author-email: andreas.siebel@it-teaching.de
License: OSI Approved :: MIT License
Download-URL: https://github.com/asbl/gamegridp/archive/master.zip
Keywords: game,education
Platform: UNKNOWN
Classifier: License :: OSI Approved :: MIT License
Classifier: Programming Language :: Python
Classifier: Development Status :: 4 - Beta
Classifier: Intended Audience :: Education
Classifier: Topic :: Education
